jdbs/__init__.py
jdbs-1.0.1.dist-info/METADATA
jdbs-1.0.1.dist-info/WHEEL
jdbs-1.0.1.dist-info/top_level.txt
jdbs-1.0.1.dist-info/RECORD
