Metadata-Version: 2.1
Name: jdbs
Version: 1.0.1
Summary: jdbs is a lightweight Python package for managing data with JSON files, offering essential database functionalities and encryption features for added security.
Home-page: https://github.com/rakibmia7254/jdbs
Author: Rakib Hossain
Author-email: rakib4ggp@gmail.com
Classifier: Development Status :: 5 - Production/Stable
Classifier: Intended Audience :: Developers
Classifier: License :: OSI Approved :: MIT License
Classifier: Programming Language :: Python :: 3
Classifier: Programming Language :: Python :: 3.6
Classifier: Programming Language :: Python :: 3.7
Classifier: Programming Language :: Python :: 3.8
Requires-Dist: pycryptodome
